CHANGELOG.md
DEVELOPMENT.md
README.md
VERSION
Plugins/ConductorUE_5.2.zip
Plugins/ConductorUE_5.3.zip
Plugins/ConductorUE_5.4.zip
Plugins/ConductorUE_5.5.zip
Plugins/ConductorUE_5.6.zip
ciounreal/VERSION
ciounreal/__init__.py
ciounreal/conductor_job_builder.py
ciounreal/conductor_job_submitter.py
ciounreal/exceptions.py
ciounreal/post_install.py
ciounreal/common/__init__.py
ciounreal/common/conductor_data.py
ciounreal/common/context.py
ciounreal/common/dependency_collector.py
ciounreal/common/unreal_utils.py
ciounreal/conductor_job/__init__.py
ciounreal/conductor_job/conductor_job.py
ciounreal/conductor_job/perforce_conductor_job.py
ciounreal/render_executors/__init__.py
ciounreal/render_executors/local_editor_render_executor.py
ciounreal/render_executors/remote_render_executor.py
ciounreal/tests/__init__.py
ciounreal/tests/unit_tests.py
ciounreal/tests/cases/__init__.py
ciounreal/tests/cases/test_conductor_data.py
ciounreal/tests/cases/test_conductor_job_submitter.py
ciounreal/tests/cases/test_dependency_collector.py
ciounreal/tests/cases/test_unreal_utils.py
ciounreal-1.0.0.dist-info/licenses/LICENSE
p4utilsforunreal/__init__.py
p4utilsforunreal/app.py
p4utilsforunreal/cli.py
p4utilsforunreal/log.py
p4utilsforunreal/perforce.py
p4utilsforunreal/tests/__init__.py
p4utilsforunreal/tests/test_p4_utils_for_unreal.py
ciounreal-1.0.0.dist-info/METADATA
ciounreal-1.0.0.dist-info/WHEEL
ciounreal-1.0.0.dist-info/top_level.txt
ciounreal-1.0.0.dist-info/RECORD
