Metadata-Version: 2.4
Name: ciounreal
Version: 1.0.0
Summary: Unreal plugin for Conductor Cloud Rendering Platform.
Home-page: https://github.com/ConductorTechnologies/ciounreal
Author: Conductor
Author-email: info@conductortech.com
Classifier: Operating System :: OS Independent
Classifier: Programming Language :: Python
Classifier: Topic :: Multimedia :: Graphics :: 3D Rendering
License-File: LICENSE
Requires-Dist: ciocore<9.0.0,>=8.3.3
Requires-Dist: cioseq<1.0.0,>=0.1.14
Requires-Dist: p4python==2024.1.2625398
Dynamic: author
Dynamic: author-email
Dynamic: classifier
Dynamic: description
Dynamic: description-content-type
Dynamic: home-page
Dynamic: license-file
Dynamic: requires-dist
Dynamic: summary
